.gitignore
.pylintrc
MANIFEST.in
README.md
requirements.txt
setup.py
example/19119_1.2.xml
example/19119_1.2_atom.xml
example/19119_2.0.xml
example/19119_2.0_multiple_datasets.xml
iso19119_nl_parser.egg-info/PKG-INFO
iso19119_nl_parser.egg-info/SOURCES.txt
iso19119_nl_parser.egg-info/dependency_links.txt
iso19119_nl_parser.egg-info/entry_points.txt
iso19119_nl_parser.egg-info/requires.txt
iso19119_nl_parser.egg-info/top_level.txt
iso19119_parser/__init__.py
iso19119_parser/cli.py
iso19119_parser/service_record.py
iso19119_parser/util.py