Metadata-Version: 1.0
Name: iso19119-nl-parser
Version: 0.0.1
Summary: PDOK service metadata (ISO19119) paraser
Home-page: UNKNOWN
Author: Anton Bakker
Author-email: anton.bakker@kadaster.nl
License: UNKNOWN
Platform: UNKNOWN
